arff_format_converter/__init__.py
arff_format_converter/arff_converter.py
arff_format_converter/logs.py
arff_format_converter/output.py
arff_format_converter/texts.py
arff_format_converter/utils.py
arff_format_converter/validate.py
arff_format_converter-1.1.1.dist-info/LICENSE
arff_format_converter-1.1.1.dist-info/METADATA
arff_format_converter-1.1.1.dist-info/WHEEL
arff_format_converter-1.1.1.dist-info/entry_points.txt
arff_format_converter-1.1.1.dist-info/top_level.txt
arff_format_converter-1.1.1.dist-info/RECORD
