Metadata-Version: 2.1
Name: arff-format-converter
Version: 1.1.1
Summary: Converts ARFF files to CSV, JSON, XML, XLSX, ORC, and parquet.
Author: Shani Sinojiya
Author-email: shanisinojiya@gmail.com
Maintainer: Shani Sinojiya
Maintainer-email: shanisinojiya@gmail.com
License: CC BY-ND 4.0
Keywords: arff,data-conversion,format-conversion,data-interchange,machine-learning,data-preprocessing,data-transformation,file-format-conversion,data-science,python-package,xml,json,csv,excel,orc,parquet,pandas,pyarrow,data-manipulation,data-export,data-import
Classifier: Programming Language :: Python :: 3
Classifier: Operating System :: OS Independent
Classifier: Intended Audience :: Developers
Classifier: Intended Audience :: Science/Research
Classifier: Programming Language :: Python :: 3 :: Only
Classifier: Natural Language :: English
License-File: LICENSE
Requires-Dist: argparse
Requires-Dist: pandas
Requires-Dist: pyarrow
Requires-Dist: scipy
